objecttostring/ObToStr.py
objecttostring/__init__.py
objecttostring/sdfsdf.py
objecttostring/test.py
objecttostring/example/__init__.py
objecttostring/example/sdfsdf.py
ObjectToString-0.2.1.dist-info/METADATA
ObjectToString-0.2.1.dist-info/WHEEL
ObjectToString-0.2.1.dist-info/top_level.txt
ObjectToString-0.2.1.dist-info/RECORD
