Metadata-Version: 2.1
Name: ObjectToString
Version: 0.2.1
Summary: ObjectToString
Author: pds
